{
  "title": "Dai Dark: The Investigation",
  "description": "Zaha Sanko investigates the dark matter",
  "author": "Q Hayashida",
  "artist": "Q Hayashida",
  "publisher": "Shogakukan",
  "publisherLinks": [],
  "tags": [],
  "contentRating": "safe",
  "altTitles": [],
  "coverImage": "cover.jpg",
  "source": "manual",
  "mangaDexId": "93f59355-6c69-416f-a5fb-84927eb31d42",
  "createdAt": "2025-09-24T18:20:15.535Z",
  "updatedAt": "2025-09-24T20:00:06.408Z",
  "totalChapters": 15,
  "chapterSource": "accurate_defaults",
  "chaptersCreatedAt": "2025-09-24T20:00:06.408Z"
}