{
  "title": "Re:Monster",
  "description": "A man reincarnated as a goblin becomes stronger",
  "author": "Kogitsune Kanekiru",
  "artist": "Haruyoshi Kobayakawa",
  "publisher": "AlphaPolis",
  "publisherLinks": [],
  "tags": [],
  "contentRating": "safe",
  "altTitles": [],
  "coverImage": "cover.jpg",
  "source": "manual",
  "mangaDexId": "b1953f80-36f7-492c-b0f8-e9dd0ad01752",
  "createdAt": "2025-09-24T17:35:06.422Z",
  "updatedAt": "2025-09-24T20:00:26.115Z",
  "totalChapters": 162,
  "chapterSource": "accurate_defaults",
  "chaptersCreatedAt": "2025-09-24T20:00:26.115Z"
}