{
  "title": "Hello World",
  "description": "The \"sci-fi love story\" film is set in Kyoto in the year 2027, and will feature famous landmarks such as Fushimi Inari Taisha and Kamo Shrine. The film centers on Naomi Katagaki, a male high school student. One day, a person who calls himself Naomi 10 years from now appears in front of the young Naomi. Together, they must change the future and save a classmate, Ruri, whom the younger Naomi starts to date in three months.",
  "authors": [],
  "artists": [],
  "year": 2019,
  "tags": [
    {
      "id": "256c8bd9-4904-4360-bf4f-508a76d67183",
      "type": "tag",
      "attributes": {
        "name": {
          "en": "Sci-Fi"
        },
        "description": {},
        "group": "genre",
        "version": 1
      },
      "relationships": []
    },
    {
      "id": "292e862b-2d17-4062-90a2-0356caa4ae27",
      "type": "tag",
      "attributes": {
        "name": {
          "en": "Time Travel"
        },
        "description": {},
        "group": "theme",
        "version": 1
      },
      "relationships": []
    },
    {
      "id": "423e2eae-a7a2-4a8b-ac03-a8351462d71d",
      "type": "tag",
      "attributes": {
        "name": {
          "en": "Romance"
        },
        "description": {},
        "group": "genre",
        "version": 1
      },
      "relationships": []
    },
    {
      "id": "b9af3a63-f058-46de-a9a0-e0c13906197a",
      "type": "tag",
      "attributes": {
        "name": {
          "en": "Drama"
        },
        "description": {},
        "group": "genre",
        "version": 1
      },
      "relationships": []
    },
    {
      "id": "eabc5b4c-6aff-42f3-b657-3e90cbd00b75",
      "type": "tag",
      "attributes": {
        "name": {
          "en": "Supernatural"
        },
        "description": {},
        "group": "theme",
        "version": 1
      },
      "relationships": []
    },
    {
      "id": "f4122d1c-3b44-44d0-9936-ff7502c39ad3",
      "type": "tag",
      "attributes": {
        "name": {
          "en": "Adaptation"
        },
        "description": {},
        "group": "format",
        "version": 1
      },
      "relationships": []
    }
  ],
  "status": "completed",
  "contentRating": "safe",
  "mangaMDId": "263b6cb0-4d7b-4a34-bb0f-5282f8968095"
}